crop_utils/__init__.py
crop_utils/html_slot_config.py
crop_utils/image.py
crop_utils/img_crop.py
crop_utils-4.3.31.dist-info/LICENSE
crop_utils-4.3.31.dist-info/METADATA
crop_utils-4.3.31.dist-info/WHEEL
crop_utils-4.3.31.dist-info/top_level.txt
crop_utils-4.3.31.dist-info/RECORD
