Metadata-Version: 2.1
Name: crop-utils
Version: 4.3.31
Summary: 主体贴边缘不扩边
Home-page: http://git.chaomy.com/libo/ecpro-utils.git
Author: libo
Author-email: 6878595@qq.com
Project-URL: Bug Tracker, https://github.com/pypa/sampleproject/issues
Classifier: Programming Language :: Python :: 3
Classifier: License :: OSI Approved :: MIT License
Classifier: Operating System :: OS Independent
Requires-Python: >=3.6
License-File: LICENSE
